docassemble.ALAnyState-0.1.0-py3.10-nspkg.pth
docassemble/ALAnyState/__init__.py
docassemble/ALAnyState/advertise_capabilities.py
docassemble/ALAnyState/al_courts.py
docassemble/ALAnyState/data/questions/any_state.yml
docassemble/ALAnyState/data/questions/custom_organization_demo.yml
docassemble/ALAnyState/data/sources/README.md
docassemble/ALAnyState/data/sources/configuration_capabilities.yml
docassemble/ALAnyState/data/sources/court_sample.xlsx
docassemble/ALAnyState/data/static/README.md
docassemble/ALAnyState/data/static/alabama-small.png
docassemble/ALAnyState/data/static/alaska-small.png
docassemble/ALAnyState/data/static/arizona-small.png
docassemble/ALAnyState/data/static/arkansas-small.png
docassemble/ALAnyState/data/static/california-small.png
docassemble/ALAnyState/data/static/colorado-small.png
docassemble/ALAnyState/data/static/colors.css
docassemble/ALAnyState/data/static/connecticut-small.png
docassemble/ALAnyState/data/static/delaware-small.png
docassemble/ALAnyState/data/static/florida-small.png
docassemble/ALAnyState/data/static/georgia-small.png
docassemble/ALAnyState/data/static/hawaii-small.png
docassemble/ALAnyState/data/static/idaho-small.png
docassemble/ALAnyState/data/static/illinois-small.png
docassemble/ALAnyState/data/static/indiana-small.png
docassemble/ALAnyState/data/static/iowa-small.png
docassemble/ALAnyState/data/static/kansas-small.png
docassemble/ALAnyState/data/static/kentucky-small.png
docassemble/ALAnyState/data/static/lmss.owl
docassemble/ALAnyState/data/static/louisiana-small.png
docassemble/ALAnyState/data/static/maine-small.png
docassemble/ALAnyState/data/static/maryland-small.png
docassemble/ALAnyState/data/static/massachusetts-small.png
docassemble/ALAnyState/data/static/michigan-small.png
docassemble/ALAnyState/data/static/minnesota-small.png
docassemble/ALAnyState/data/static/mississippi-small.png
docassemble/ALAnyState/data/static/missouri-small.png
docassemble/ALAnyState/data/static/montana-small.png
docassemble.ALAnyState-0.1.0.dist-info/LICENSE
docassemble.ALAnyState-0.1.0.dist-info/METADATA
docassemble.ALAnyState-0.1.0.dist-info/WHEEL
docassemble.ALAnyState-0.1.0.dist-info/namespace_packages.txt
docassemble.ALAnyState-0.1.0.dist-info/top_level.txt
docassemble.ALAnyState-0.1.0.dist-info/RECORD
