Metadata-Version: 2.1
Name: docassemble.ALAnyState
Version: 0.1.0
Summary: A plugin for docassemble.ALWeaver and runtime for docassemble.AssemblyLine
Home-page: https://docassemble.org
Author: Quinten Steenhuis
Author-email: qsteenhuis@suffolk.edu
License: The MIT License (MIT)
License-File: LICENSE
